datahub_agent_context/__init__.py
datahub_agent_context/_version.py
datahub_agent_context/context.py
datahub_agent_context/py.typed
datahub_agent_context/langchain_tools/__init__.py
datahub_agent_context/langchain_tools/builder.py
datahub_agent_context/mcp_tools/__init__.py
datahub_agent_context/mcp_tools/_token_estimator.py
datahub_agent_context/mcp_tools/base.py
datahub_agent_context/mcp_tools/descriptions.py
datahub_agent_context/mcp_tools/documents.py
datahub_agent_context/mcp_tools/domains.py
datahub_agent_context/mcp_tools/entities.py
datahub_agent_context/mcp_tools/get_me.py
datahub_agent_context/mcp_tools/helpers.py
datahub_agent_context/mcp_tools/lineage.py
datahub_agent_context/mcp_tools/owners.py
datahub_agent_context/mcp_tools/queries.py
datahub_agent_context/mcp_tools/search.py
datahub_agent_context/mcp_tools/structured_properties.py
datahub_agent_context/mcp_tools/tags.py
datahub_agent_context/mcp_tools/terms.py
datahub_agent_context/mcp_tools/gql/__init__.py
datahub_agent_context/mcp_tools/gql/document_search.gql
datahub_agent_context/mcp_tools/gql/document_semantic_search.gql
datahub_agent_context/mcp_tools/gql/entity_details.gql
datahub_agent_context/mcp_tools/gql/queries.gql
datahub_agent_context/mcp_tools/gql/query_entity.gql
datahub_agent_context/mcp_tools/gql/read_documents.gql
datahub_agent_context/mcp_tools/gql/search.gql
datahub_agent_context-1.3.1.10.dist-info/METADATA
datahub_agent_context-1.3.1.10.dist-info/WHEEL
datahub_agent_context-1.3.1.10.dist-info/top_level.txt
datahub_agent_context-1.3.1.10.dist-info/RECORD
