Metadata-Version: 2.4
Name: datahub-agent-context
Version: 1.3.1.10
Summary: DataHub Agent Context - MCP Tools for AI Agents
Home-page: https://datahub.io/
License: Apache License 2.0
Project-URL: Documentation, https://datahubproject.io/docs/
Project-URL: Source, https://github.com/datahub-project/datahub
Project-URL: Changelog, https://github.com/datahub-project/datahub/releases
Classifier: Development Status :: 5 - Production/Stable
Classifier: Programming Language :: Python
Classifier: Programming Language :: Python :: 3
Classifier: Programming Language :: Python :: 3 :: Only
Classifier: Programming Language :: Python :: 3.9
Classifier: Programming Language :: Python :: 3.10
Classifier: Programming Language :: Python :: 3.11
Classifier: Programming Language :: Python :: 3.12
Classifier: Programming Language :: Python :: 3.13
Classifier: Intended Audience :: Developers
Classifier: Intended Audience :: Information Technology
Classifier: Intended Audience :: System Administrators
Classifier: License :: OSI Approved
Classifier: License :: OSI Approved :: Apache Software License
Classifier: Operating System :: Unix
Classifier: Operating System :: POSIX :: Linux
Classifier: Environment :: Console
Classifier: Environment :: MacOS X
Classifier: Topic :: Software Development
Requires-Python: >=3.9
Requires-Dist: acryl-datahub==1.3.1.10
Requires-Dist: google-re2<2.0,>=1.0
Requires-Dist: json-repair<1.0.0,>=0.25.0
Requires-Dist: jmespath<2.0.0,>=1.0.0
Requires-Dist: h11<1.0,>=0.16
Requires-Dist: cachetools<7.0.0,>=5.0.0
Requires-Dist: httpcore<2.0,>=1.0.9
Requires-Dist: pydantic<3.0.0,>=2.0.0
Provides-Extra: dev
Requires-Dist: mypy==1.17.1; extra == "dev"
Requires-Dist: tox<5.0.0,>=4.0.0; extra == "dev"
Requires-Dist: types-PyYAML<7.0.0,>=6.0.0; extra == "dev"
Requires-Dist: pytest-cov<7.0.0,>=2.8.0; extra == "dev"
Requires-Dist: types-toml<1.0.0,>=0.10.0; extra == "dev"
Requires-Dist: types-requests<3.0.0,>=2.0.0; extra == "dev"
Requires-Dist: types-jmespath<2.0.0,>=1.0.0; extra == "dev"
Requires-Dist: pytest<9.0.0,>=8.3.4; extra == "dev"
Requires-Dist: types-cachetools<7.0.0,>=5.0.0; extra == "dev"
Requires-Dist: ruff==0.11.7; extra == "dev"
Provides-Extra: langchain
Requires-Dist: langchain-core<2.0.0,>=1.2.7; extra == "langchain"
Dynamic: classifier
Dynamic: description
Dynamic: description-content-type
Dynamic: home-page
Dynamic: license
Dynamic: project-url
Dynamic: provides-extra
Dynamic: requires-dist
Dynamic: requires-python
Dynamic: summary
